tcbench/Deterministic_CNN.py
tcbench/Deterministic_MLR.py
tcbench/__init__.py
tcbench/ai_track_processor.py
tcbench/baselines/__init__.py
tcbench/baselines/baselines.py
tcbench/metrics/__init__.py
tcbench/metrics/metrics.py
tcbench/utils/ERA5_downloader_interface.py
tcbench/utils/ML_functions.py
tcbench/utils/__init__.py
tcbench/utils/constants.py
tcbench/utils/dat_to_xr.py
tcbench/utils/data_lib.py
tcbench/utils/toolbox.py
tcbenchmark/Deterministic_CNN.py
tcbenchmark/Deterministic_MLR.py
tcbenchmark/__init__.py
tcbenchmark/ai_track_processor.py
tcbenchmark/baselines/__init__.py
tcbenchmark/baselines/baselines.py
tcbenchmark/metrics/__init__.py
tcbenchmark/metrics/metrics.py
tcbenchmark/utils/ERA5_downloader_interface.py
tcbenchmark/utils/ML_functions.py
tcbenchmark/utils/__init__.py
tcbenchmark/utils/constants.py
tcbenchmark/utils/dat_to_xr.py
tcbenchmark/utils/data_lib.py
tcbenchmark/utils/toolbox.py
TCBenchmark-0.0.2.dist-info/LICENSE
TCBenchmark-0.0.2.dist-info/METADATA
TCBenchmark-0.0.2.dist-info/WHEEL
TCBenchmark-0.0.2.dist-info/top_level.txt
TCBenchmark-0.0.2.dist-info/RECORD
