Metadata-Version: 2.1
Name: TCBenchmark
Version: 0.0.2
Summary: Python platform and benchmark dataset for data-driven tropical cyclone studies.
Home-page: https://wp.unil.ch/dawn/
Maintainer: Milton S. Gomez
Maintainer-email: milton.gomez@unil.ch
License: MIT
Project-URL: Bug Tracker, https://github.com/msgomez06/TCBench_Alpha/issues
Project-URL: Documentation, https://github.com/msgomez06/TCBench_Alpha/wiki
Project-URL: Source Code, https://github.com/msgomez06/TCBench_Alpha
Classifier: Intended Audience :: Science/Research
Classifier: Intended Audience :: Developers
Classifier: Intended Audience :: Education
Classifier: License :: OSI Approved :: MIT License
Classifier: Programming Language :: Python
Classifier: Topic :: Scientific/Engineering :: Atmospheric Science
Classifier: Topic :: Scientific/Engineering :: Artificial Intelligence
Classifier: Development Status :: 3 - Alpha
Classifier: Operating System :: Microsoft :: Windows
Classifier: Operating System :: Unix
Classifier: Operating System :: MacOS
Classifier: Programming Language :: Python :: 3
Classifier: Programming Language :: Python :: 3.9
Classifier: Programming Language :: Python :: 3.10
Classifier: Programming Language :: Python :: 3.11
Classifier: Programming Language :: Python :: 3.12
Requires-Python: >=3.9
License-File: LICENSE
